<ArrayOfCustomRuleSignal xmlns="http://schemas.datacontract.org/2004/07/Indicator.Resource" xmlns:i="http://www.w3.org/2001/XMLSchema-instance"><CustomRuleSignal><Operator/><OperatorSelected i:nil="true"/><_allsignals xmlns:a="http://schemas.datacontract.org/2004/07/TradersToolbox.Core.Serializable"><a:Signal i:type="a:SignalValueRAW"><a:Args/><a:Children i:nil="true"/><a:GroupId i:nil="true"/><a:Key>Open</a:Key><a:MarketNumber>0</a:MarketNumber><a:SymbolId><a:IsServerSide>false</a:IsServerSide><a:Name>@Vix</a:Name><a:Shift>0</a:Shift><a:Timeframe>1D</a:Timeframe></a:SymbolId><a:Text_custom i:nil="true"/><a:Type>BaseValuable</a:Type><a:activeForEntry_internal>false</a:activeForEntry_internal><a:activeForExit_internal>false</a:activeForExit_internal><a:isRequired_internal>false</a:isRequired_internal></a:Signal><a:Signal i:type="a:SignalValueRAW"><a:Args/><a:Children i:nil="true"/><a:GroupId i:nil="true"/><a:Key>High</a:Key><a:MarketNumber>0</a:MarketNumber><a:SymbolId><a:IsServerSide>false</a:IsServerSide><a:Name>@Vix</a:Name><a:Shift>0</a:Shift><a:Timeframe>1D</a:Timeframe></a:SymbolId><a:Text_custom i:nil="true"/><a:Type>BaseValuable</a:Type><a:activeForEntry_internal>false</a:activeForEntry_internal><a:activeForExit_internal>false</a:activeForExit_internal><a:isRequired_internal>false</a:isRequired_internal></a:Signal><a:Signal i:type="a:SignalValueRAW"><a:Args/><a:Children i:nil="true"/><a:GroupId i:nil="true"/><a:Key>Low</a:Key><a:MarketNumber>0</a:MarketNumber><a:SymbolId><a:IsServerSide>false</a:IsServerSide><a:Name>@Vix</a:Name><a:Shift>0</a:Shift><a:Timeframe>1D</a:Timeframe></a:SymbolId><a:Text_custom i:nil="true"/><a:Type>BaseValuable</a:Type><a:activeForEntry_internal>false</a:activeForEntry_internal><a:activeForExit_internal>false</a:activeForExit_internal><a:isRequired_internal>false</a:isRequired_internal></a:Signal><a:Signal i:type="a:SignalValueRAW"><a:Args/><a:Children i:nil="true"/><a:GroupId i:nil="true"/><a:Key>Close</a:Key><a:MarketNumber>0</a:MarketNumber><a:SymbolId><a:IsServerSide>false</a:IsServerSide><a:Name>@Vix</a:Name><a:Shift>0</a:Shift><a:Timeframe>1D</a:Timeframe></a:SymbolId><a:Text_custom i:nil="true"/><a:Type>BaseValuable</a:Type><a:activeForEntry_internal>false</a:activeForEntry_internal><a:activeForExit_internal>false</a:activeForExit_internal><a:isRequired_internal>false</a:isRequired_internal></a:Signal><a:Signal i:type="a:SignalValueWinLast"><a:Args><a:SignalArg><a:BaseValue>10</a:BaseValue><a:IncrementStep>0</a:IncrementStep><a:Key>Length</a:Key><a:LastValue>10</a:LastValue><a:Max>1000</a:Max><a:Min>1</a:Min><a:Type>Static</a:Type></a:SignalArg></a:Args><a:Children><a:Signal i:type="a:SignalValueRAW"><a:Args/><a:Children i:nil="true"/><a:GroupId i:nil="true"/><a:Key>Close</a:Key><a:MarketNumber>0</a:MarketNumber><a:SymbolId><a:IsServerSide>false</a:IsServerSide><a:Name>@Vix</a:Name><a:Shift>0</a:Shift><a:Timeframe>1D</a:Timeframe></a:SymbolId><a:Text_custom i:nil="true"/><a:Type>BaseValuable</a:Type><a:activeForEntry_internal>false</a:activeForEntry_internal><a:activeForExit_internal>false</a:activeForExit_internal><a:isRequired_internal>false</a:isRequired_internal></a:Signal></a:Children><a:GroupId i:nil="true"/><a:Key>WinLast</a:Key><a:MarketNumber>0</a:MarketNumber><a:SymbolId><a:IsServerSide>false</a:IsServerSide><a:Name>@Vix</a:Name><a:Shift>0</a:Shift><a:Timeframe>1D</a:Timeframe></a:SymbolId><a:Text_custom i:nil="true"/><a:Type>BaseValuable</a:Type><a:activeForEntry_internal>false</a:activeForEntry_internal><a:activeForExit_internal>false</a:activeForExit_internal><a:isRequired_internal>false</a:isRequired_internal></a:Signal><a:Signal i:type="a:SignalValueRSI"><a:Args><a:SignalArg><a:BaseValue>10</a:BaseValue><a:IncrementStep>0</a:IncrementStep><a:Key>Length</a:Key><a:LastValue>10</a:LastValue><a:Max>1000</a:Max><a:Min>1</a:Min><a:Type>Static</a:Type></a:SignalArg></a:Args><a:Children><a:Signal i:type="a:SignalValueRAW"><a:Args/><a:Children i:nil="true"/><a:GroupId i:nil="true"/><a:Key>Close</a:Key><a:MarketNumber>0</a:MarketNumber><a:SymbolId><a:IsServerSide>false</a:IsServerSide><a:Name>@Vix</a:Name><a:Shift>0</a:Shift><a:Timeframe>1D</a:Timeframe></a:SymbolId><a:Text_custom i:nil="true"/><a:Type>BaseValuable</a:Type><a:activeForEntry_internal>false</a:activeForEntry_internal><a:activeForExit_internal>false</a:activeForExit_internal><a:isRequired_internal>false</a:isRequired_internal></a:Signal></a:Children><a:GroupId i:nil="true"/><a:Key>Rsi</a:Key><a:MarketNumber>0</a:MarketNumber><a:SymbolId><a:IsServerSide>false</a:IsServerSide><a:Name>@Vix</a:Name><a:Shift>0</a:Shift><a:Timeframe>1D</a:Timeframe></a:SymbolId><a:Text_custom i:nil="true"/><a:Type>BaseValuable</a:Type><a:activeForEntry_internal>false</a:activeForEntry_internal><a:activeForExit_internal>false</a:activeForExit_internal><a:isRequired_internal>false</a:isRequired_internal></a:Signal></_allsignals><_operator/></CustomRuleSignal><CustomRuleSignal><Operator>+</Operator><OperatorSelected i:nil="true"/><_allsignals xmlns:a="http://schemas.datacontract.org/2004/07/TradersToolbox.Core.Serializable"><a:Signal i:type="a:SignalValueRAW"><a:Args/><a:Children i:nil="true"/><a:GroupId i:nil="true"/><a:Key>Open</a:Key><a:MarketNumber>0</a:MarketNumber><a:SymbolId><a:IsServerSide>false</a:IsServerSide><a:Name>@Vix</a:Name><a:Shift>0</a:Shift><a:Timeframe>1D</a:Timeframe></a:SymbolId><a:Text_custom i:nil="true"/><a:Type>BaseValuable</a:Type><a:activeForEntry_internal>false</a:activeForEntry_internal><a:activeForExit_internal>false</a:activeForExit_internal><a:isRequired_internal>false</a:isRequired_internal></a:Signal><a:Signal i:type="a:SignalValueRAW"><a:Args/><a:Children i:nil="true"/><a:GroupId i:nil="true"/><a:Key>High</a:Key><a:MarketNumber>0</a:MarketNumber><a:SymbolId><a:IsServerSide>false</a:IsServerSide><a:Name>@Vix</a:Name><a:Shift>0</a:Shift><a:Timeframe>1D</a:Timeframe></a:SymbolId><a:Text_custom i:nil="true"/><a:Type>BaseValuable</a:Type><a:activeForEntry_internal>false</a:activeForEntry_internal><a:activeForExit_internal>false</a:activeForExit_internal><a:isRequired_internal>false</a:isRequired_internal></a:Signal><a:Signal i:type="a:SignalValueRAW"><a:Args/><a:Children i:nil="true"/><a:GroupId i:nil="true"/><a:Key>Low</a:Key><a:MarketNumber>0</a:MarketNumber><a:SymbolId><a:IsServerSide>false</a:IsServerSide><a:Name>@Vix</a:Name><a:Shift>0</a:Shift><a:Timeframe>1D</a:Timeframe></a:SymbolId><a:Text_custom i:nil="true"/><a:Type>BaseValuable</a:Type><a:activeForEntry_internal>false</a:activeForEntry_internal><a:activeForExit_internal>false</a:activeForExit_internal><a:isRequired_internal>false</a:isRequired_internal></a:Signal><a:Signal i:type="a:SignalValueRAW"><a:Args/><a:Children i:nil="true"/><a:GroupId i:nil="true"/><a:Key>Close</a:Key><a:MarketNumber>0</a:MarketNumber><a:SymbolId><a:IsServerSide>false</a:IsServerSide><a:Name>@Vix</a:Name><a:Shift>0</a:Shift><a:Timeframe>1D</a:Timeframe></a:SymbolId><a:Text_custom i:nil="true"/><a:Type>BaseValuable</a:Type><a:activeForEntry_internal>false</a:activeForEntry_internal><a:activeForExit_internal>false</a:activeForExit_internal><a:isRequired_internal>false</a:isRequired_internal></a:Signal><a:Signal i:type="a:SignalValueWinLast"><a:Args><a:SignalArg><a:BaseValue>10</a:BaseValue><a:IncrementStep>0</a:IncrementStep><a:Key>Length</a:Key><a:LastValue>10</a:LastValue><a:Max>1000</a:Max><a:Min>1</a:Min><a:Type>Static</a:Type></a:SignalArg></a:Args><a:Children><a:Signal i:type="a:SignalValueRAW"><a:Args/><a:Children i:nil="true"/><a:GroupId i:nil="true"/><a:Key>Close</a:Key><a:MarketNumber>0</a:MarketNumber><a:SymbolId><a:IsServerSide>false</a:IsServerSide><a:Name>@Vix</a:Name><a:Shift>0</a:Shift><a:Timeframe>1D</a:Timeframe></a:SymbolId><a:Text_custom i:nil="true"/><a:Type>BaseValuable</a:Type><a:activeForEntry_internal>false</a:activeForEntry_internal><a:activeForExit_internal>false</a:activeForExit_internal><a:isRequired_internal>false</a:isRequired_internal></a:Signal></a:Children><a:GroupId i:nil="true"/><a:Key>WinLast</a:Key><a:MarketNumber>0</a:MarketNumber><a:SymbolId><a:IsServerSide>false</a:IsServerSide><a:Name>@Vix</a:Name><a:Shift>0</a:Shift><a:Timeframe>1D</a:Timeframe></a:SymbolId><a:Text_custom i:nil="true"/><a:Type>BaseValuable</a:Type><a:activeForEntry_internal>false</a:activeForEntry_internal><a:activeForExit_internal>false</a:activeForExit_internal><a:isRequired_internal>false</a:isRequired_internal></a:Signal><a:Signal i:type="a:SignalValueRSI"><a:Args><a:SignalArg><a:BaseValue>10</a:BaseValue><a:IncrementStep>0</a:IncrementStep><a:Key>Length</a:Key><a:LastValue>10</a:LastValue><a:Max>1000</a:Max><a:Min>1</a:Min><a:Type>Static</a:Type></a:SignalArg></a:Args><a:Children><a:Signal i:type="a:SignalValueRAW"><a:Args/><a:Children i:nil="true"/><a:GroupId i:nil="true"/><a:Key>Close</a:Key><a:MarketNumber>0</a:MarketNumber><a:SymbolId><a:IsServerSide>false</a:IsServerSide><a:Name>@Vix</a:Name><a:Shift>0</a:Shift><a:Timeframe>1D</a:Timeframe></a:SymbolId><a:Text_custom i:nil="true"/><a:Type>BaseValuable</a:Type><a:activeForEntry_internal>false</a:activeForEntry_internal><a:activeForExit_internal>false</a:activeForExit_internal><a:isRequired_internal>false</a:isRequired_internal></a:Signal></a:Children><a:GroupId i:nil="true"/><a:Key>Rsi</a:Key><a:MarketNumber>0</a:MarketNumber><a:SymbolId><a:IsServerSide>false</a:IsServerSide><a:Name>@Vix</a:Name><a:Shift>0</a:Shift><a:Timeframe>1D</a:Timeframe></a:SymbolId><a:Text_custom i:nil="true"/><a:Type>BaseValuable</a:Type><a:activeForEntry_internal>false</a:activeForEntry_internal><a:activeForExit_internal>false</a:activeForExit_internal><a:isRequired_internal>false</a:isRequired_internal></a:Signal></_allsignals><_operator>+</_operator></CustomRuleSignal></ArrayOfCustomRuleSignal>